rummikubconsole/__init__.py
rummikubconsole/__main__.py
rummikubconsole/_console.py
rummikubconsole/_tile_source.py
rummikubconsole/_types.py
rummikubconsole/_utils.py
rummikubconsole/gamestate.py
rummikubconsole-2.0.0.dist-info/METADATA
rummikubconsole-2.0.0.dist-info/WHEEL
rummikubconsole-2.0.0.dist-info/entry_points.txt
rummikubconsole-2.0.0.dist-info/licenses/LICENSE.txt
rummikubconsole-2.0.0.dist-info/RECORD
