Metadata-Version: 2.4
Name: RummikubConsole
Version: 2.0.0
Summary: Rummikub solver console with multi-game support and persistence.
Project-URL: GitHub, https://github.com/mjpieters/RummikubConsole
Project-URL: Issues, https://github.com/mjpieters/RummikubConsole/issues
Project-URL: Changelog, https://github.com/mjpieters/RummikubConsole/blob/master/CHANGELOG.md
Author-email: Martijn Pieters <mj@zopatista.com>
License-Expression: MIT
License-File: LICENSE.txt
Classifier: Development Status :: 5 - Production/Stable
Classifier: Environment :: Console
Classifier: Intended Audience :: End Users/Desktop
Classifier: License :: OSI Approved :: MIT License
Classifier: Programming Language :: Python
Classifier: Programming Language :: Python :: 3
Classifier: Programming Language :: Python :: Implementation :: CPython
Classifier: Topic :: Games/Entertainment :: Board Games
Requires-Python: >=3.11
Requires-Dist: click
Requires-Dist: platformdirs>=4.3.6
Requires-Dist: rummikub-solver>=1.0.0rc2
